<?xml version='1.0' encoding='UTF-8'?><Version product="openanalytics-open" apiStyle="RPC" name="2020-09-28" isolationType="outer"><ErrorMapping exceptionExpress=""><ErrorCodes /></ErrorMapping><Apis><Api name="GetDatabaseObjects" /><Api name="GetDatabaseObjectByName" /><Api name="GetDatabaseObjectById" /><Api name="GrantAdminPrivilege" /><Api name="getDatabaseObjectsByFilter" /><Api name="GetTableObjectsByName" /><Api name="ListPrivileges" /><Api name="GetTableObjectsByDatabaseId" /><Api name="GetDatabaseTags" /><Api name="CountDatabasesByNameAndTags" /><Api name="GetColumnObjects" /><Api name="GetDatabaseObjectsByNamePrefix" /><Api name="GetDatabaseObjectsByNameAndTags" /><Api name="GetAllDatabases" /><Api name="GetPartition" /><Api name="GetPartitions" /><Api name="RevokePrivileges" /><Api name="DropPartition" /><Api name="AddPartitions" /><Api name="GrantPrivileges" /><Api name="GetTable" /><Api name="DropDatabase" /><Api name="GetDatabase" /><Api name="GetAllTables" /><Api name="DropTable" /><Api name="AlterDatabase" /><Api name="AlterTable" /><Api name="CreateDatabase" /><Api name="CreateTable" /></Apis></Version>
